llm_cli/__init__.py
llm_cli/__main__.py
llm_cli/cli.py
llm_cli/streaming_markdown.py
llm_cli/markdown_renderer/__init__.py
llm_cli/markdown_renderer/terminal_renderer.py
streamlm-0.1.10.dist-info/METADATA
streamlm-0.1.10.dist-info/WHEEL
streamlm-0.1.10.dist-info/entry_points.txt
streamlm-0.1.10.dist-info/licenses/LICENSE
streamlm-0.1.10.dist-info/RECORD
