Metadata-Version: 2.4
Name: streamlm
Version: 0.1.10
Summary: A command-line interface for interacting with various Large Language Models with streaming markdown output
Project-URL: Homepage, https://github.com/jeffmylife/streamlm
Project-URL: Repository, https://github.com/jeffmylife/streamlm
Project-URL: Issues, https://github.com/jeffmylife/streamlm/issues
Project-URL: Changelog, https://github.com/jeffmylife/streamlm/releases
Author-email: Jeffrey Lemoine <jeffmylife@gmail.com>
License: MIT
License-File: LICENSE
Keywords: ai,anthropic,cli,deepseek,gemini,llm,markdown,ollama,openai,streaming,xai
Classifier: Development Status :: 4 - Beta
Classifier: Environment :: Console
Classifier: Intended Audience :: Developers
Classifier: Intended Audience :: End Users/Desktop
Classifier: License :: OSI Approved :: MIT License
Classifier: Operating System :: OS Independent
Classifier: Programming Language :: Python :: 3
Classifier: Programming Language :: Python :: 3.10
Classifier: Programming Language :: Python :: 3.11
Classifier: Programming Language :: Python :: 3.12
Classifier: Programming Language :: Python :: 3.13
Classifier: Topic :: Scientific/Engineering :: Artificial Intelligence
Classifier: Topic :: Software Development :: Libraries :: Python Modules
Classifier: Topic :: System :: Shells
Classifier: Topic :: Text Processing :: Markup :: Markdown
Classifier: Topic :: Utilities
Requires-Python: >=3.10
Requires-Dist: litellm>=1.30.3
Requires-Dist: mistune>=3.0.0
Requires-Dist: openai>=1.0.0
Requires-Dist: requests>=2.31.0
Requires-Dist: rich-click>=1.7.0
Requires-Dist: rich>=13.7.0
Requires-Dist: typer>=0.9.0
